{"website": "https://www.odoo.com/page/employees", "description": "\nHuman Resources Management\n==========================\n\nThis application enables you to manage important aspects of your company's staff and other details such as their skills, contacts, working time...\n\n\nYou can manage:\n---------------\n* Employees and hierarchies : You can define your employee with User and display hierarchies\n* HR Departments\n* HR Jobs\n    ", "sequence": 21, "demo": ["hr_demo.xml"], "depends": ["base_setup", "mail", "resource", "board"], "auto_install": false, "data": ["security/hr_security.xml", "security/ir.model.access.csv", "hr_view.xml", "hr_installer.xml", "hr_data.xml", "res_config_view.xml", "mail_hr_view.xml", "res_users_view.xml", "views/hr.xml"], "demo_xml": [], "icon": "/hr/static/description/icon.png", "category": "Human Resources", "web": false, "init_xml": [], "name": "Employee Directory", "license": "AGPL-3", "author": "OpenERP SA", "update_xml": [], "summary": "Jobs, Departments, Employees Details", "application": true, "version": "8.0.1.1", "post_load": null, "test": ["test/hr_users.yml", "test/open2recruit2close_job.yml", "test/hr_demo.yml"], "module_path": "/mnt/data/home/mdupont/experiments/odoo/addons/hr", "qweb": ["static/src/xml/suggestions.xml"], "installable": true}