{"website": "https://www.odoo.com/page/accounting", "description": "\nThis module allows to use several analytic plans according to the general journal.\n==================================================================================\n\nHere multiple analytic lines are created when the invoice or the entries\nare confirmed.\n\nFor example, you can define the following analytic structure:\n-------------------------------------------------------------\n  * **Projects**\n      * Project 1\n          + SubProj 1.1\n          \n          + SubProj 1.2\n\n      * Project 2\n      \n  * **Salesman**\n      * Eric\n      \n      * Fabien\n\nHere, we have two plans: Projects and Salesman. An invoice line must be able to write analytic entries in the 2 plans: SubProj 1.1 and Fabien. The amount can also be split.\n \nThe following example is for an invoice that touches the two subprojects and assigned to one salesman:\n~~~~~~~~~~~~~~~~~~~~~~~~~~~~~~~~~~~~~~~~~~~~~~~~~~~~~~~~~~~~~~~~~~~~~~~~~~~~~~~~~~~~~~~~~~~~~~~~~~~~~~\n**Plan1:**\n\n    * SubProject 1.1 : 50%\n    \n    * SubProject 1.2 : 50%\n    \n**Plan2:**\n    Eric: 100%\n\nSo when this line of invoice will be confirmed, it will generate 3 analytic lines,for one account entry.\n\nThe analytic plan validates the minimum and maximum percentage at the time of creation of distribution models.\n        ", "sequence": 100, "demo": [], "depends": ["account", "account_analytic_default"], "auto_install": false, "data": ["security/account_analytic_plan_security.xml", "security/ir.model.access.csv", "account_analytic_plans_view.xml", "account_analytic_plans_report.xml", "wizard/analytic_plan_create_model_view.xml", "wizard/account_crossovered_analytic_view.xml", "views/report_crossoveredanalyticplans.xml", "views/account_analytic_plans.xml"], "demo_xml": [], "icon": "/base/static/description/icon.png", "category": "Accounting & Finance", "web": false, "init_xml": [], "name": "Multiple Analytic Plans", "license": "AGPL-3", "author": "OpenERP SA", "update_xml": [], "summary": "", "application": false, "version": "8.0.1.0", "post_load": null, "test": ["test/acount_analytic_plans_report.yml"], "module_path": "/mnt/data/home/mdupont/experiments/odoo/addons/account_analytic_plans", "installable": true}